{
  "last_run": "2026-04-06T09:51:43",
  "last_run_date": "2026-04-06",
  "run_mode": "UPDATE",
  "aif_filing_date": "2025-03-27",
  "as_at_date": "2024-12-31",
  "has_aif": true,
  "sw_covered_to": "2026-03-23",
  "new_filings_this_run": 1,
  "presentation_url": "https://pub-e6549556cd074443b759440dcb9b174f.r2.dev/onboarding/MARI/2026-04-06_Marimaca-Investor-Feature.pdf",
  "presentation_local": "C:\\Users\\Admin\\Mineral Media\\Mineral Media Shared Library - Documents\\13 - DS AI\\2. SEDAR+\\3. Company Onboarding\\Results\\MARI\\pdfs\\Presentations\\2026-04-06_Marimaca-Investor-Feature.pdf",
  "presentation_size_kb": 3325,
  "presentation_date": "June 2025"
}